setup.py
mongoobject/__init__.py
mongoobject.egg-info/PKG-INFO
mongoobject.egg-info/SOURCES.txt
mongoobject.egg-info/dependency_links.txt
mongoobject.egg-info/requires.txt
mongoobject.egg-info/top_level.txt