Metadata-Version: 1.0
Name: mongoobject
Version: 0.1
Summary: Mongo Object
Home-page: http://github.com/binarydud/mongoobject
Author: Matt George
Author-email: mgeorge@gmail.com
License: MIT
Platform: UNKNOWN
Classifier: Development Status :: 3 - Alpha
Classifier: Environment :: Console
Classifier: Intended Audience :: Developers
Classifier: License :: OSI Approved :: MIT License
Classifier: Operating System :: OS Independent
Classifier: Programming Language :: Python
